CLIP_pk_de_repeat/CLIP_Rela.py
CLIP_pk_de_repeat/PK_img_de_repeat.py
CLIP_pk_de_repeat/__init__.py
CLIP_pk_de_repeat-0.1.3.dist-info/METADATA
CLIP_pk_de_repeat-0.1.3.dist-info/WHEEL
CLIP_pk_de_repeat-0.1.3.dist-info/top_level.txt
CLIP_pk_de_repeat-0.1.3.dist-info/RECORD
