Metadata-Version: 2.1
Name: CLIP_pk_de_repeat
Version: 0.1.3
Summary: 使用CLIP对图像进行去重
Author: Ayleea
Author-email: zshigerc@163.com
Classifier: Programming Language :: Python :: 3
Classifier: License :: OSI Approved :: MIT License
Classifier: Operating System :: OS Independent
Requires-Python: >=3.10
Requires-Dist: torch
Requires-Dist: h5py
Requires-Dist: numpy
Requires-Dist: transformers
Requires-Dist: scikit-learn
